LICENSE.rst
README.rst
setup.py
src/thruflo/__init__.py
src/thruflo.webapp.egg-info/PKG-INFO
src/thruflo.webapp.egg-info/SOURCES.txt
src/thruflo.webapp.egg-info/dependency_links.txt
src/thruflo.webapp.egg-info/entry_points.txt
src/thruflo.webapp.egg-info/namespace_packages.txt
src/thruflo.webapp.egg-info/not-zip-safe
src/thruflo.webapp.egg-info/requires.txt
src/thruflo.webapp.egg-info/top_level.txt
src/thruflo/webapp/__init__.py
src/thruflo/webapp/cache.py
src/thruflo/webapp/template.py
src/thruflo/webapp/utils.py
src/thruflo/webapp/web.py
src/thruflo/webapp/demo/__init__.py
src/thruflo/webapp/demo/app.py
src/thruflo/webapp/demo/templates/foo.tmpl