Metadata-Version: 1.0
Name: thruflo.webapp
Version: 0.1.3
Summary: Yet another WSGI web app framework
Home-page: http://github.com/thruflo/thruflo.webapp
Author: James Arthur
Author-email: thruflo@googlemail.com
License: Public Domain (http://creativecommons.org/publicdomain/zero/1.0/legalcode)
Platform: UNKNOWN
Classifier: Development Status :: 3 - Alpha
Classifier: Environment :: Web Environment
Classifier: Programming Language :: Python
